RPA_PDF.libspec
RPA/PDF/__init__.py
RPA/PDF/assets/Inter-Bold.ttf
RPA/PDF/assets/Inter-BoldItalic.ttf
RPA/PDF/assets/Inter-Italic.ttf
RPA/PDF/assets/Inter-Regular.ttf
RPA/PDF/keywords/__init__.py
RPA/PDF/keywords/context.py
RPA/PDF/keywords/document.py
RPA/PDF/keywords/finder.py
RPA/PDF/keywords/model.py
rpaframework_pdf-7.3.1.dist-info/LICENSE
rpaframework_pdf-7.3.1.dist-info/METADATA
rpaframework_pdf-7.3.1.dist-info/WHEEL
rpaframework_pdf-7.3.1.dist-info/RECORD
